vcode/__init__.py
vcode/main.py
verification_code-1.0.0.dist-info/DESCRIPTION.rst
verification_code-1.0.0.dist-info/METADATA
verification_code-1.0.0.dist-info/RECORD
verification_code-1.0.0.dist-info/WHEEL
verification_code-1.0.0.dist-info/metadata.json
verification_code-1.0.0.dist-info/top_level.txt
